StockFetch/Main.sh
StockFetch/Pyfinance.py
StockFetch/__init__.py
StockFetch/cli.py
stockfetch-1.0.2.dist-info/METADATA
stockfetch-1.0.2.dist-info/WHEEL
stockfetch-1.0.2.dist-info/entry_points.txt
stockfetch-1.0.2.dist-info/RECORD
