Metadata-Version: 2.4
Name: stockfetch
Version: 1.0.2
Summary: Neofetch for stocks
Project-URL: Homepage, https://github.com/Avni2000/StockFetch
Project-URL: Repository, https://github.com/Avni2000/StockFetch
Author-email: Avni Badiwale <avnibadiwale@gmail.com>
License: MIT
Classifier: Development Status :: 4 - Beta
Classifier: Intended Audience :: End Users/Desktop
Classifier: License :: OSI Approved :: MIT License
Classifier: Programming Language :: Python :: 3
Classifier: Programming Language :: Python :: 3.8
Classifier: Programming Language :: Python :: 3.9
Classifier: Programming Language :: Python :: 3.10
Classifier: Programming Language :: Python :: 3.11
Classifier: Programming Language :: Python :: 3.12
Requires-Python: >=3.8
Requires-Dist: numpy>=1.20.0
Requires-Dist: pillow>=8.0.0
Requires-Dist: requests>=2.25.0
Requires-Dist: yfinance>=0.2.0
